nat20/__init__.py
nat20/__main__.py
nat20/constants.py
nat20/link.py
nat20/messages.py
nat20/msglib.py
nat20-0.1.0.dist-info/LICENSE
nat20-0.1.0.dist-info/METADATA
nat20-0.1.0.dist-info/WHEEL
nat20-0.1.0.dist-info/RECORD
